ponddy_auth/__init__.py
ponddy_auth/apps.py
ponddy_auth/authentication.py
ponddy_auth/permissions.py
ponddy_auth/utils.py
ponddy_auth-0.1.5.dist-info/METADATA
ponddy_auth-0.1.5.dist-info/WHEEL
ponddy_auth-0.1.5.dist-info/top_level.txt
ponddy_auth-0.1.5.dist-info/RECORD
