Metadata-Version: 2.1
Name: ponddy-auth
Version: 0.1.5
Summary: The Ponddy Auth SSO authentication library
Home-page: https://github.com/samwuTW/ponddy-auth
Author: lambdaTW
Author-email: lambda@lambda.tw
License: MIT
Keywords: Ponddy Auth SSO
Platform: UNKNOWN
Classifier: Programming Language :: Python :: 3.7
Requires-Dist: Django
Requires-Dist: djangorestframework
Requires-Dist: python-jose
Requires-Dist: requests
